pyflow_cse_asu/EvaluationMetrics.py
pyflow_cse_asu/Layers.py
pyflow_cse_asu/Model.py
pyflow_cse_asu/Utilities.py
pyflow_cse_asu/Visualizer.py
pyflow_cse_asu/activations.py
pyflow_cse_asu/alexnet.py
pyflow_cse_asu/dataset.py
pyflow_cse_asu/lenet-5.py
pyflow_cse_asu/libraries.py
pyflow_cse_asu/loss.py
pyflow_cse_asu-1.1.2.dist-info/LICENSE.txt
pyflow_cse_asu-1.1.2.dist-info/METADATA
pyflow_cse_asu-1.1.2.dist-info/WHEEL
pyflow_cse_asu-1.1.2.dist-info/top_level.txt
pyflow_cse_asu-1.1.2.dist-info/RECORD
