Metadata-Version: 2.1
Name: pyflow-cse-asu
Version: 1.1.2
Summary: CSE463 Neural Networks Project
Home-page: https://github.com/MahmoudOsama97/DL-Framework-Project
Author: Mahmoud Osama
Author-email: omarashinawy@gmail.com
License: UNKNOWN
Platform: UNKNOWN
Classifier: Programming Language :: Python :: 3
Classifier: License :: OSI Approved :: GNU General Public License v3 (GPLv3)
Classifier: Operating System :: OS Independent
Requires-Python: >=3.6
